{
    "ean": "7052870178269",
    "id": "60114007",
    "name": "Laminatgulv 1-stav Grand Prime Champs Elysees - BerryAlloc",
    "brandName": "BerryAlloc",
    "measurements": {
        "netContent": {
            "unit": "PAK",
            "value": 2.323
        },
        "grossWeight": 23.8,
        "grossDimensions": {
            "width": {
                "unit": "m",
                "value": 0.265,
                "unitCode": "MT",
                "unitLocalized": "m"
            },
            "height": {
                "unit": "m",
                "value": 0.053,
                "unitCode": "MT",
                "unitLocalized": "m"
            },
            "length": {
                "unit": "m",
                "value": 2.449,
                "unitCode": "MT",
                "unitLocalized": "m"
            }
        }
    },
    "images": [
        {
            "url": "https://public.keskofiles.com/f/btt/ASSET_MISC_25143790",
            "type": "PRODUCT"
        },
        {
            "url": "https://public.keskofiles.com/f/btt/ASSET_MISC_23169693",
            "type": "ADDITIONAL"
        },
        {
            "url": "https://public.keskofiles.com/f/btt/ASSET_MISC_24892269",
            "type": "ADDITIONAL_1"
        },
        {
            "url": "https://public.keskofiles.com/f/btt/ASSET_MISC_26418484",
            "type": "ADDITIONAL_2"
        },
        {
            "url": "https://public.keskofiles.com/f/btt/ASSET_MISC_30938915",
            "type": "ADDITIONAL_3"
        },
        {
            "url": "https://public.keskofiles.com/f/btt/ASSET_MISC_30938917",
            "type": "ADDITIONAL_4"
        }
    ],
    "categories": [
        {
            "salesCategoryIdentifier": "CLS_BM_eComProductLvl_3224059",
            "name": "Laminatgulv",
            "url": "gulv/laminatgulv"
        },
        {
            "salesCategoryIdentifier": "CLS_BM_eComLvl1_3223876",
            "name": "Gulv",
            "url": "gulv"
        }
    ],
    "relatedEans": []
}